hypotesis_savior/__init__.py
hypotesis_savior/core.py
hypotesis_savior-0.1.2.dist-info/METADATA
hypotesis_savior-0.1.2.dist-info/WHEEL
hypotesis_savior-0.1.2.dist-info/top_level.txt
hypotesis_savior-0.1.2.dist-info/RECORD
